LICENSE
README.md
setup.py
normflow/__init__.py
normflow/utils.py
normflow.egg-info/PKG-INFO
normflow.egg-info/SOURCES.txt
normflow.egg-info/dependency_links.txt
normflow.egg-info/top_level.txt
normflow/common/__init__.py
normflow/common/invertible.py
normflow/couplings/__init__.py
normflow/couplings/additive.py
normflow/couplings/affine.py
normflow/couplings/autoregressive.py
normflow/couplings/base.py
normflow/flows/__init__.py
normflow/flows/base.py
normflow/hli/__init__.py
normflow/splits/__init__.py
normflow/splits/base.py
normflow/splits/even.py
normflow/splits/masked.py
normflow/splits/random_select.py
normflow/transforms/__init__.py
normflow/transforms/actnorm.py
normflow/transforms/base.py
normflow/transforms/composite.py
normflow/transforms/coupling.py
normflow/transforms/identity.py
normflow/transforms/permutations/__init__.py
normflow/transforms/permutations/base.py
normflow/transforms/permutations/index.py
normflow/transforms/permutations/random.py
normflow/transforms/permutations/reverse.py